Metadata-Version: 2.1
Name: gridly-cli
Version: 0.1.8
Summary: Gridly CLI 1st version
Home-page: https://gridly.com
Author: Gridly
Author-email: cn@localizedirect.com
License: MIT
Download-URL: https://github.com/gridly-spreadsheet-CMS/gridly-cli/archive/refs/tags/0.1.8.tar.gz
Keywords: GRIDLY,CLI,CMS,GRIDLY CLI
Platform: UNKNOWN
Classifier: Development Status :: 3 - Alpha
Classifier: Intended Audience :: Developers
Classifier: Topic :: Software Development :: Build Tools
Classifier: License :: OSI Approved :: MIT License
Classifier: Programming Language :: Python :: 3
Classifier: Programming Language :: Python :: 3.4
Classifier: Programming Language :: Python :: 3.5
Classifier: Programming Language :: Python :: 3.6
